FireCaptcha/__init__.py
FireCaptcha/captcha.py
FireCaptcha-0.0.2.2.dist-info/LICENSE
FireCaptcha-0.0.2.2.dist-info/METADATA
FireCaptcha-0.0.2.2.dist-info/WHEEL
FireCaptcha-0.0.2.2.dist-info/top_level.txt
FireCaptcha-0.0.2.2.dist-info/RECORD
